{
       "id": "06ed4ac9cb",
       "type": "rice",
       "ingredients": [
              {
                     "object": "oil",
                     "state": "juice"
              },
              {
                     "object": "shallot",
                     "state": "chopped"
              },
              {
                     "object": "rice",
                     "state": "grain"
              },
              {
                     "object": "turmeric",
                     "state": "ground"
              },
              {
                     "object": "coriander",
                     "state": "ground"
              },
              {
                     "object": "stick",
                     "state": "whole"
              },
              {
                     "object": "salt",
                     "state": "ground"
              },
              {
                     "object": "cumin",
                     "state": "ground"
              },
              {
                     "object": "broth",
                     "state": "thick liquid"
              },
              {
                     "object": "lime",
                     "state": "whole"
              },
              {
                     "object": "currant",
                     "state": "ground"
              }
       ]
}