{
       "id": "00e268bfa6",
       "type": "bread",
       "ingredients": [
              {
                     "object": "butter",
                     "state": "creamy"
              },
              {
                     "object": "sugar",
                     "state": "ground"
              },
              {
                     "object": "flavoring",
                     "state": "juice"
              },
              {
                     "object": "egg",
                     "state": "whole raw"
              },
              {
                     "object": "baking powder",
                     "state": "ground"
              },
              {
                     "object": "baking soda",
                     "state": "ground"
              },
              {
                     "object": "salt",
                     "state": "ground"
              },
              {
                     "object": "flour",
                     "state": "ground"
              },
              {
                     "object": "strawberry",
                     "state": "crushed"
              }
       ]
}