[
    {
        "input_nodes": [
            {
                "label": "tomatoes",
                "states": [
                    "minced"
                ],
                "ingredients": [],
                "container": "jar"
            },
            {
                "label": "spoon",
                "states": [
                    "empty"
                ],
                "ingredients": [],
                "container": null
            }
        ],
        "motion_node": "scoop and pour",
        "output_nodes": [
            {
                "label": "cutting board",
                "states": [],
                "ingredients": [
                    "tomatoes",
                    "onion"
                ],
                "container": null
            },
            {
                "label": "tomatoes",
                "states": [
                    "minced"
                ],
                "ingredients": [],
                "container": "cutting board"
            }
        ]
    },
    {
        "input_nodes": [
            {
                "label": "bowl",
                "states": [],
                "ingredients": [
                    "oil"
                ],
                "container": null
            },
            {
                "label": "cutting board",
                "states": [],
                "ingredients": [
                    "tomatoes"
                ],
                "container": null
            },
            {
                "label": "tomatoes",
                "states": [
                    "minced"
                ],
                "ingredients": [],
                "container": "cutting board"
            }
        ],
        "motion_node": "scrape",
        "output_nodes": [
            {
                "label": "bowl",
                "states": [],
                "ingredients": [
                    "oil",
                    "tomatoes"
                ],
                "container": null
            },
            {
                "label": "cutting board",
                "states": [
                    "empty"
                ],
                "ingredients": [],
                "container": null
            },
            {
                "label": "tomatoes",
                "states": [
                    "minced"
                ],
                "ingredients": [],
                "container": "bowl"
            }
        ]
    },
    {
        "input_nodes": [
            {
                "label": "pot",
                "states": [],
                "ingredients": [
                    "rice",
                    "oil"
                ],
                "container": "stove"
            },
            {
                "label": "bowl",
                "states": [],
                "ingredients": [
                    "tomatoes"
                ],
                "container": null
            },
            {
                "label": "tomatoes",
                "states": [
                    "minced"
                ],
                "ingredients": [],
                "container": "bowl"
            }
        ],
        "motion_node": "scrape",
        "output_nodes": [
            {
                "label": "pot",
                "states": [],
                "ingredients": [
                    "rice",
                    "oil",
                    "tomatoes"
                ],
                "container": "stove"
            },
            {
                "label": "tomatoes",
                "states": [
                    "minced"
                ],
                "ingredients": [],
                "container": "pot"
            }
        ]
    },
    {
        "input_nodes": [
            {
                "label": "pot",
                "states": [],
                "ingredients": [
                    "rice",
                    "oil",
                    "tomatoes"
                ],
                "container": "stove"
            },
            {
                "label": "bowl",
                "states": [],
                "ingredients": [
                    "water"
                ],
                "container": null
            },
            {
                "label": "water",
                "states": [],
                "ingredients": [],
                "container": "bowl"
            }
        ],
        "motion_node": "pour",
        "output_nodes": [
            {
                "label": "pot",
                "states": [],
                "ingredients": [
                    "rice",
                    "oil",
                    "tomatoes",
                    "water"
                ],
                "container": "stove"
            },
            {
                "label": "water",
                "states": [],
                "ingredients": [],
                "container": "pot"
            }
        ]
    },
    {
        "input_nodes": [
            {
                "label": "pot",
                "states": [
                    "heated"
                ],
                "ingredients": [],
                "container": "stove"
            },
            {
                "label": "bowl",
                "states": [],
                "ingredients": [
                    "oil"
                ],
                "container": null
            },
            {
                "label": "oil",
                "states": [],
                "ingredients": [],
                "container": "bowl"
            }
        ],
        "motion_node": "pour",
        "output_nodes": [
            {
                "label": "pot",
                "states": [],
                "ingredients": [
                    "oil"
                ],
                "container": "stove"
            }
        ]
    },
    {
        "input_nodes": [
            {
                "label": "pot",
                "states": [],
                "ingredients": [
                    "rice",
                    "oil",
                    "tomatoes",
                    "water"
                ],
                "container": "stove"
            }
        ],
        "motion_node": "cook",
        "output_nodes": [
            {
                "label": "pot",
                "states": [
                    "partly cooked"
                ],
                "ingredients": [
                    "rice",
                    "oil",
                    "tomatoes",
                    "water"
                ],
                "container": "stove"
            }
        ]
    },
    {
        "input_nodes": [
            {
                "label": "pot",
                "states": [],
                "ingredients": [
                    "oil"
                ],
                "container": "stove"
            },
            {
                "label": "bowl",
                "states": [],
                "ingredients": [
                    "rice"
                ],
                "container": null
            },
            {
                "label": "rice",
                "states": [
                    "uncooked"
                ],
                "ingredients": [],
                "container": "bowl"
            },
            {
                "label": "spoon",
                "states": [],
                "ingredients": [],
                "container": null
            }
        ],
        "motion_node": "pour",
        "output_nodes": [
            {
                "label": "pot",
                "states": [],
                "ingredients": [
                    "rice",
                    "oil"
                ],
                "container": "stove"
            },
            {
                "label": "rice",
                "states": [
                    "uncooked"
                ],
                "ingredients": [],
                "container": "pot"
            }
        ]
    },
    {
        "input_nodes": [
            {
                "label": "pot",
                "states": [
                    "partly cooked"
                ],
                "ingredients": [
                    "rice",
                    "oil",
                    "tomatoes",
                    "water"
                ],
                "container": "stove"
            },
            {
                "label": "bowl",
                "states": [],
                "ingredients": [
                    "salt"
                ],
                "container": null
            },
            {
                "label": "salt",
                "states": [
                    "granulated"
                ],
                "ingredients": [],
                "container": "bowl"
            }
        ],
        "motion_node": "pour",
        "output_nodes": [
            {
                "label": "pot",
                "states": [],
                "ingredients": [
                    "rice",
                    "water",
                    "oil",
                    "salt",
                    "tomatoes"
                ],
                "container": "stove"
            }
        ]
    },
    {
        "input_nodes": [
            {
                "label": "pot",
                "states": [],
                "ingredients": [
                    "rice",
                    "oil"
                ],
                "container": "stove"
            },
            {
                "label": "rice",
                "states": [
                    "uncooked"
                ],
                "ingredients": [],
                "container": "pot"
            },
            {
                "label": "spoon",
                "states": [],
                "ingredients": [],
                "container": null
            }
        ],
        "motion_node": "cook and stir",
        "output_nodes": [
            {
                "label": "pot",
                "states": [],
                "ingredients": [
                    "rice",
                    "oil"
                ],
                "container": "stove"
            },
            {
                "label": "rice",
                "states": [
                    "toasted"
                ],
                "ingredients": [],
                "container": "pot"
            }
        ]
    },
    {
        "input_nodes": [
            {
                "label": "pot",
                "states": [],
                "ingredients": [
                    "rice",
                    "water",
                    "oil",
                    "salt",
                    "tomatoes"
                ],
                "container": "stove"
            },
            {
                "label": "rice",
                "states": [
                    "toasted"
                ],
                "ingredients": [],
                "container": "pot"
            }
        ],
        "motion_node": "cook",
        "output_nodes": [
            {
                "label": "pot",
                "states": [
                    "partly cooked"
                ],
                "ingredients": [
                    "rice",
                    "water",
                    "oil",
                    "salt",
                    "tomatoes"
                ],
                "container": "stove"
            }
        ]
    },
    {
        "input_nodes": [
            {
                "label": "pot",
                "states": [
                    "partly cooked"
                ],
                "ingredients": [
                    "rice",
                    "water",
                    "oil",
                    "salt",
                    "tomatoes"
                ],
                "container": "stove"
            },
            {
                "label": "pot lid",
                "states": [],
                "ingredients": [],
                "container": null
            }
        ],
        "motion_node": "cover",
        "output_nodes": [
            {
                "label": "pot",
                "states": [
                    "covered"
                ],
                "ingredients": [
                    "rice",
                    "water",
                    "oil",
                    "salt",
                    "tomatoes"
                ],
                "container": "stove"
            },
            {
                "label": "pot lid",
                "states": [],
                "ingredients": [],
                "container": "pan"
            }
        ]
    },
    {
        "input_nodes": [
            {
                "label": "stove",
                "states": [
                    "on"
                ],
                "ingredients": [],
                "container": "pot"
            },
            {
                "label": "pot",
                "states": [
                    "covered"
                ],
                "ingredients": [
                    "rice",
                    "water",
                    "oil",
                    "salt",
                    "tomatoes"
                ],
                "container": "stove"
            }
        ],
        "motion_node": "cook",
        "output_nodes": [
            {
                "label": "pot",
                "states": [
                    "covered"
                ],
                "ingredients": [
                    "rice"
                ],
                "container": "stove"
            },
            {
                "label": "rice",
                "states": [
                    "cooked"
                ],
                "ingredients": [
                    "oil",
                    "rice",
                    "tomatoes",
                    "water",
                    "salt",
                    "lime zest"
                ],
                "container": "pot"
            }
        ]
    },
    {
        "input_nodes": [
            {
                "label": "pot",
                "states": [],
                "ingredients": [
                    "rice"
                ],
                "container": "stove"
            },
            {
                "label": "rice",
                "states": [
                    "cooked"
                ],
                "ingredients": [
                    "oil",
                    "rice",
                    "tomatoes",
                    "water",
                    "salt",
                    "lime zest"
                ],
                "container": "pot"
            },
            {
                "label": "fork",
                "states": [],
                "ingredients": [],
                "container": null
            }
        ],
        "motion_node": "stir",
        "output_nodes": [
            {
                "label": "rice",
                "states": [
                    "fluffed"
                ],
                "ingredients": [
                    "oil",
                    "rice",
                    "tomatoes",
                    "water",
                    "salt",
                    "lime zest"
                ],
                "container": "pot"
            }
        ]
    },
    {
        "input_nodes": [
            {
                "label": "pot",
                "states": [],
                "ingredients": [
                    "rice"
                ],
                "container": "stove"
            },
            {
                "label": "rice",
                "states": [
                    "fluffed"
                ],
                "ingredients": [
                    "oil",
                    "rice",
                    "tomatoes",
                    "water",
                    "salt",
                    "lime zest"
                ],
                "container": "pot"
            }
        ],
        "motion_node": "pour",
        "output_nodes": [
            {
                "label": "rice",
                "states": [
                    "cooked"
                ],
                "ingredients": [
                    "oil",
                    "rice",
                    "tomatoes",
                    "water",
                    "salt",
                    "lime zest",
                    "lime juice"
                ],
                "container": "pot"
            }
        ]
    },
    {
        "input_nodes": [
            {
                "label": "pot",
                "states": [],
                "ingredients": [
                    "rice"
                ],
                "container": "stove"
            },
            {
                "label": "measuring cup",
                "states": [],
                "ingredients": [
                    "parsley"
                ],
                "container": null
            },
            {
                "label": "parsley",
                "states": [
                    "chopped"
                ],
                "ingredients": [],
                "container": "measuring cup"
            },
            {
                "label": "rice",
                "states": [
                    "cooked"
                ],
                "ingredients": [
                    "oil",
                    "rice",
                    "tomatoes",
                    "water",
                    "salt",
                    "lime zest",
                    "lime juice"
                ],
                "container": "pot"
            }
        ],
        "motion_node": "pour",
        "output_nodes": [
            {
                "label": "rice",
                "states": [
                    "cooked"
                ],
                "ingredients": [
                    "oil",
                    "rice",
                    "tomatoes",
                    "water",
                    "salt",
                    "lime zest",
                    "lime juice",
                    "parsley"
                ],
                "container": "pot"
            }
        ]
    },
    {
        "input_nodes": [
            {
                "label": "pot",
                "states": [],
                "ingredients": [
                    "rice"
                ],
                "container": "stove"
            },
            {
                "label": "rice",
                "states": [
                    "cooked"
                ],
                "ingredients": [
                    "oil",
                    "rice",
                    "tomatoes",
                    "water",
                    "salt",
                    "lime zest",
                    "lime juice",
                    "parsley"
                ],
                "container": "pot"
            },
            {
                "label": "spoon",
                "states": [],
                "ingredients": [],
                "container": null
            }
        ],
        "motion_node": "stir",
        "output_nodes": [
            {
                "label": "pot",
                "states": [],
                "ingredients": [
                    "garlic"
                ],
                "container": null
            },
            {
                "label": "garlic",
                "states": [],
                "ingredients": [
                    "oil",
                    "rice",
                    "tomatoes",
                    "water",
                    "salt",
                    "lime zest",
                    "lime juice",
                    "parsley"
                ],
                "container": "pot"
            }
        ]
    },
    {
        "input_nodes": [
            {
                "label": "pot",
                "states": [],
                "ingredients": [
                    "garlic"
                ],
                "container": null
            },
            {
                "label": "garlic",
                "states": [],
                "ingredients": [
                    "oil",
                    "rice",
                    "tomatoes",
                    "water",
                    "salt",
                    "lime zest",
                    "lime juice",
                    "parsley"
                ],
                "container": "pot"
            },
            {
                "label": "plate",
                "states": [
                    "empty"
                ],
                "ingredients": [],
                "container": null
            },
            {
                "label": "spoon",
                "states": [],
                "ingredients": [],
                "container": null
            }
        ],
        "motion_node": "scoop and pour",
        "output_nodes": [
            {
                "label": "plate",
                "states": [],
                "ingredients": [
                    "garlic"
                ],
                "container": null
            },
            {
                "label": "garlic",
                "states": [],
                "ingredients": [
                    "oil",
                    "rice",
                    "tomatoes",
                    "water",
                    "salt",
                    "lime zest",
                    "lime juice",
                    "parsley"
                ],
                "container": "plate"
            }
        ]
    }
]