[
    {
        "input_nodes": [
            {
                "label": "container",
                "states": [],
                "ingredients": [
                    "sugar"
                ],
                "container": null
            },
            {
                "label": "sugar",
                "states": [
                    "granulated"
                ],
                "ingredients": [],
                "container": "container"
            },
            {
                "label": "bowl",
                "states": [
                    "empty"
                ],
                "ingredients": [],
                "container": null
            }
        ],
        "motion_node": "pour",
        "output_nodes": [
            {
                "label": "bowl",
                "states": [],
                "ingredients": [
                    "sugar"
                ],
                "container": null
            },
            {
                "label": "sugar",
                "states": [
                    "granulated"
                ],
                "ingredients": [],
                "container": "bowl"
            }
        ]
    },
    {
        "input_nodes": [
            {
                "label": "pepper",
                "states": [
                    "unpeeled",
                    "whole"
                ],
                "ingredients": [],
                "container": null
            },
            {
                "label": "knife",
                "states": [],
                "ingredients": [],
                "container": null
            }
        ],
        "motion_node": "peel",
        "output_nodes": [
            {
                "label": "onion",
                "states": [
                    "whole",
                    "peeled"
                ],
                "ingredients": [],
                "container": null
            }
        ]
    },
    {
        "input_nodes": [
            {
                "label": "pepper",
                "states": [
                    "unpeeled",
                    "whole"
                ],
                "ingredients": [],
                "container": null
            },
            {
                "label": "cutting board",
                "states": [
                    "empty"
                ],
                "ingredients": [],
                "container": null
            }
        ],
        "motion_node": "pick-and-place",
        "output_nodes": [
            {
                "label": "pepper",
                "states": [
                    "unpeeled",
                    "whole"
                ],
                "ingredients": [],
                "container": "cutting board"
            }
        ]
    },
    {
        "input_nodes": [
            {
                "label": "bowl",
                "states": [],
                "ingredients": [
                    "sugar"
                ],
                "container": null
            },
            {
                "label": "sugar",
                "states": [
                    "granulated"
                ],
                "ingredients": [],
                "container": "bowl"
            },
            {
                "label": "mixing bowl",
                "states": [],
                "ingredients": [
                    "mayonnaise"
                ],
                "container": null
            }
        ],
        "motion_node": "pour",
        "output_nodes": [
            {
                "label": "mixing bowl",
                "states": [],
                "ingredients": [
                    "sugar",
                    "mayonnaise"
                ],
                "container": null
            },
            {
                "label": "sugar",
                "states": [
                    "granulated"
                ],
                "ingredients": [],
                "container": "mixing bowl"
            },
            {
                "label": "bowl",
                "states": [
                    "empty"
                ],
                "ingredients": [],
                "container": null
            }
        ]
    },
    {
        "input_nodes": [
            {
                "label": "jar",
                "states": [
                    "opened"
                ],
                "ingredients": [
                    "mayonnaise"
                ],
                "container": null
            },
            {
                "label": "mayonnaise",
                "states": [
                    "creamy"
                ],
                "ingredients": [],
                "container": "jar"
            },
            {
                "label": "measuring cup",
                "states": [
                    "empty"
                ],
                "ingredients": [],
                "container": null
            }
        ],
        "motion_node": "scoop",
        "output_nodes": [
            {
                "label": "measuring cup",
                "states": [],
                "ingredients": [
                    "mayonnaise"
                ],
                "container": null
            },
            {
                "label": "mayonnaise",
                "states": [
                    "creamy"
                ],
                "ingredients": [],
                "container": "measuring cup"
            }
        ]
    },
    {
        "input_nodes": [
            {
                "label": "cutting board",
                "states": [
                    "empty"
                ],
                "ingredients": [],
                "container": null
            },
            {
                "label": "onion",
                "states": [
                    "peeled",
                    "whole"
                ],
                "ingredients": [],
                "container": null
            }
        ],
        "motion_node": "pick-and-place",
        "output_nodes": [
            {
                "label": "cutting board",
                "states": [],
                "ingredients": [
                    "onion"
                ],
                "container": null
            },
            {
                "label": "onion",
                "states": [
                    "whole",
                    "peeled"
                ],
                "ingredients": [],
                "container": "cutting board"
            }
        ]
    },
    {
        "input_nodes": [
            {
                "label": "pepper",
                "states": [
                    "unpeeled",
                    "whole"
                ],
                "ingredients": [],
                "container": "cutting board"
            }
        ],
        "motion_node": "peel",
        "output_nodes": [
            {
                "label": "pepper",
                "states": [
                    "whole",
                    "peeled"
                ],
                "ingredients": [],
                "container": "cutting board"
            }
        ]
    },
    {
        "input_nodes": [
            {
                "label": "mixing bowl",
                "states": [],
                "ingredients": [
                    "sugar",
                    "mayonnaise"
                ],
                "container": null
            },
            {
                "label": "bowl",
                "states": [],
                "ingredients": [
                    "vinegar"
                ],
                "container": null
            },
            {
                "label": "vinegar",
                "states": [
                    "liquid"
                ],
                "ingredients": [],
                "container": "bowl"
            }
        ],
        "motion_node": "pour",
        "output_nodes": [
            {
                "label": "mixing bowl",
                "states": [],
                "ingredients": [
                    "sugar",
                    "vinegar",
                    "mayonnaise"
                ],
                "container": null
            },
            {
                "label": "vinegar",
                "states": [
                    "liquid"
                ],
                "ingredients": [],
                "container": "mixing bowl"
            },
            {
                "label": "bowl",
                "states": [
                    "empty"
                ],
                "ingredients": [],
                "container": null
            }
        ]
    },
    {
        "input_nodes": [
            {
                "label": "bowl",
                "states": [
                    "empty"
                ],
                "ingredients": [],
                "container": null
            },
            {
                "label": "measuring cup",
                "states": [],
                "ingredients": [
                    "mayonnaise"
                ],
                "container": null
            },
            {
                "label": "mayonnaise",
                "states": [
                    "creamy"
                ],
                "ingredients": [],
                "container": "measuring cup"
            }
        ],
        "motion_node": "pour",
        "output_nodes": [
            {
                "label": "mixing bowl",
                "states": [],
                "ingredients": [
                    "mayonnaise"
                ],
                "container": null
            },
            {
                "label": "mayonnaise",
                "states": [
                    "creamy"
                ],
                "ingredients": [],
                "container": "mixing bowl"
            },
            {
                "label": "measuring cup",
                "states": [
                    "empty"
                ],
                "ingredients": [],
                "container": null
            }
        ]
    },
    {
        "input_nodes": [
            {
                "label": "onion",
                "states": [
                    "whole",
                    "peeled"
                ],
                "ingredients": [],
                "container": "cutting board"
            },
            {
                "label": "knife",
                "states": [],
                "ingredients": [],
                "container": null
            }
        ],
        "motion_node": "chop",
        "output_nodes": [
            {
                "label": "onion",
                "states": [
                    "chopped"
                ],
                "ingredients": [],
                "container": "cutting board"
            }
        ]
    },
    {
        "input_nodes": [
            {
                "label": "knife",
                "states": [],
                "ingredients": [],
                "container": null
            },
            {
                "label": "pepper",
                "states": [
                    "peeled",
                    "whole"
                ],
                "ingredients": [],
                "container": "cutting board"
            }
        ],
        "motion_node": "chop",
        "output_nodes": [
            {
                "label": "pepper",
                "states": [
                    "chopped"
                ],
                "ingredients": [],
                "container": "cutting board"
            }
        ]
    },
    {
        "input_nodes": [
            {
                "label": "mixing bowl",
                "states": [],
                "ingredients": [
                    "sugar",
                    "vinegar",
                    "mayonnaise"
                ],
                "container": null
            },
            {
                "label": "sugar",
                "states": [
                    "granulated"
                ],
                "ingredients": [],
                "container": "mixing bowl"
            },
            {
                "label": "mayonnaise",
                "states": [
                    "creamy"
                ],
                "ingredients": [],
                "container": "mixing bowl"
            },
            {
                "label": "vinegar",
                "states": [
                    "liquid"
                ],
                "ingredients": [],
                "container": "mixing bowl"
            },
            {
                "label": "spatula",
                "states": [],
                "ingredients": [],
                "container": null
            }
        ],
        "motion_node": "mix",
        "output_nodes": [
            {
                "label": "salad dressing",
                "states": [
                    "creamy",
                    "mixed"
                ],
                "ingredients": [
                    "sugar",
                    "vinegar",
                    "mayonnaise"
                ],
                "container": "mixing bowl"
            }
        ]
    },
    {
        "input_nodes": [
            {
                "label": "salad bowl",
                "states": [
                    "empty"
                ],
                "ingredients": [],
                "container": null
            },
            {
                "label": "cutting board",
                "states": [],
                "ingredients": [
                    "onion"
                ],
                "container": null
            },
            {
                "label": "onion",
                "states": [
                    "chopped"
                ],
                "ingredients": [],
                "container": "cutting board"
            }
        ],
        "motion_node": "scoop and pour",
        "output_nodes": [
            {
                "label": "salad bowl",
                "states": [],
                "ingredients": [
                    "onion"
                ],
                "container": null
            },
            {
                "label": "onion",
                "states": [
                    "chopped"
                ],
                "ingredients": [],
                "container": "salad bowl"
            },
            {
                "label": "cutting board",
                "states": [
                    "empty"
                ],
                "ingredients": [],
                "container": null
            }
        ]
    },
    {
        "input_nodes": [
            {
                "label": "salad bowl",
                "states": [],
                "ingredients": [
                    "onion"
                ],
                "container": null
            },
            {
                "label": "pepper",
                "states": [
                    "chopped"
                ],
                "ingredients": [],
                "container": "cutting board"
            }
        ],
        "motion_node": "scoop and pour",
        "output_nodes": [
            {
                "label": "salad bowl",
                "states": [],
                "ingredients": [
                    "pepper",
                    "onion"
                ],
                "container": null
            },
            {
                "label": "pepper",
                "states": [
                    "chopped"
                ],
                "ingredients": [],
                "container": "salad bowl"
            },
            {
                "label": "cutting board",
                "states": [
                    "empty"
                ],
                "ingredients": [],
                "container": null
            }
        ]
    },
    {
        "input_nodes": [
            {
                "label": "salad bowl",
                "states": [],
                "ingredients": [
                    "pepper",
                    "onion"
                ],
                "container": null
            },
            {
                "label": "salad dressing",
                "states": [
                    "creamy",
                    "mixed"
                ],
                "ingredients": [
                    "sugar",
                    "vinegar",
                    "mayonnaise"
                ],
                "container": "mixing bowl"
            },
            {
                "label": "spatula",
                "states": [],
                "ingredients": [],
                "container": null
            }
        ],
        "motion_node": "pour and scrape",
        "output_nodes": [
            {
                "label": "salad bowl",
                "states": [],
                "ingredients": [
                    "pepper",
                    "onion"
                ],
                "container": null
            },
            {
                "label": "salad dressing",
                "states": [
                    "creamy"
                ],
                "ingredients": [
                    "sugar",
                    "vinegar",
                    "mayonnaise"
                ],
                "container": "salad bowl"
            }
        ]
    },
    {
        "input_nodes": [
            {
                "label": "salad bowl",
                "states": [],
                "ingredients": [
                    "pepper",
                    "onion"
                ],
                "container": null
            },
            {
                "label": "salad dressing",
                "states": [
                    "creamy"
                ],
                "ingredients": [
                    "sugar",
                    "vinegar",
                    "mayonnaise"
                ],
                "container": "salad bowl"
            },
            {
                "label": "pepper",
                "states": [
                    "chopped"
                ],
                "ingredients": [],
                "container": "salad bowl"
            },
            {
                "label": "onion",
                "states": [
                    "chopped"
                ],
                "ingredients": [],
                "container": "salad bowl"
            },
            {
                "label": "spatula",
                "states": [],
                "ingredients": [],
                "container": null
            }
        ],
        "motion_node": "mix",
        "output_nodes": [
            {
                "label": "salad",
                "states": [
                    "mixed"
                ],
                "ingredients": [
                    "sugar",
                    "mayonnaise",
                    "onion",
                    "vinegar",
                    "pepper"
                ],
                "container": "salad bowl"
            },
            {
                "label": "coleslaw",
                "states": [
                    "mixed"
                ],
                "ingredients": [
                    "sugar",
                    "mayonnaise",
                    "onion",
                    "vinegar",
                    "pepper"
                ],
                "container": "salad bowl"
            }
        ]
    }
]