{
       "id": "1077bb4325",
       "type": "noodle",
       "ingredients": [
              {
                     "object": "noodle",
                     "state": "processed raw"
              },
              {
                     "object": "oil",
                     "state": "juice"
              },
              {
                     "object": "chicken",
                     "state": "baked"
              },
              {
                     "object": "apple",
                     "state": "halved"
              },
              {
                     "object": "pineapple",
                     "state": "diced"
              },
              {
                     "object": "celery",
                     "state": "diced"
              },
              {
                     "object": "cucumber",
                     "state": "sliced"
              },
              {
                     "object": "onion",
                     "state": "diced"
              },
              {
                     "object": "craisin",
                     "state": "dried"
              },
              {
                     "object": "seed",
                     "state": "grain"
              },
              {
                     "object": "seed",
                     "state": "grain"
              },
              {
                     "object": "water",
                     "state": "juice"
              },
              {
                     "object": "soy sauce",
                     "state": "sauce"
              },
              {
                     "object": "vinegar",
                     "state": "juice"
              },
              {
                     "object": "sugar",
                     "state": "ground"
              },
              {
                     "object": "ginger",
                     "state": "grated"
              },
              {
                     "object": "cayenne",
                     "state": "ground"
              }
       ]
}